LICENSE
dyndns_updater/__init__.py
dyndns_updater/__main__.py
dyndns_updater/extractor.py
dyndns_updater/locator.py
dyndns_updater/updater.py
dyndns_updater/utils.py
dyndns_updater-0.2.0.dist-info/entry_points.txt
dyndns_updater-0.2.0.dist-info/LICENSE
dyndns_updater-0.2.0.dist-info/WHEEL
dyndns_updater-0.2.0.dist-info/METADATA
dyndns_updater-0.2.0.dist-info/RECORD
