Metadata-Version: 2.1
Name: dyndns-updater
Version: 0.2.0
Summary: standalone DNS updater for Gandi
Home-page: https://github.com/zar3bski/dynDNS_updater
Keywords: dns,gandi
Author: David Zarebski
Author-email: zarebskidavid@gmail.com
Requires-Python: >=3.6,<4.0
Classifier: Programming Language :: Python :: 3
Classifier: Programming Language :: Python :: 3.6
Classifier: Programming Language :: Python :: 3.7
Classifier: Programming Language :: Python :: 3.8
Classifier: Programming Language :: Python :: 3.9
Requires-Dist: PyYAML (>=5.4.1,<6.0.0)
Requires-Dist: dnspython (>=2.1.0,<3.0.0)
Requires-Dist: requests (>=2.25.1,<3.0.0)
Requires-Dist: schedule (>=1.1.0,<2.0.0)
Project-URL: Repository, https://github.com/zar3bski/dynDNS_updater
